KCE/__init__.py
KCE-3.14159265358.dist-info/LICENSE
KCE-3.14159265358.dist-info/METADATA
KCE-3.14159265358.dist-info/WHEEL
KCE-3.14159265358.dist-info/top_level.txt
KCE-3.14159265358.dist-info/RECORD
