Metadata-Version: 2.1
Name: KCE
Version: 3.14159265358
Summary: This is a project of the group KCE
Home-page: UNKNOWN
Author: Taebin, Yang
Author-email: ksa.yangtaebin@gmail.com
License: KCE
Platform: UNKNOWN
Classifier: Programming Language :: Python :: 3
